Workbook

Sheet Cover
B2: NextEra Energy, Inc. (NYSE: NEE)
B3: Equity Research Initiation Report
B5: Rating: SELL
B6: 12-Month Price Target: $36.20
B7: Current Share Price: $83.85
B8: Upside / (Downside): -57%
B9: Sector: Utilities
B10: Industry: Regulated Utilities & Renewable Energy
B12: Investment Summary
B13: This report initiates coverage on NextEra Energy, Inc. with a SELL rating. The analysis was initially framed around a BUY hypothesis, driven by expectations of interest-rate normalization, declining cost of capital, and valuation multiple expansion across regulated and renewable utility assets. However, following a full bottom-up operating model, discounted cash flow valuation, and trading multiples analysis, the intrinsic value implied by fundamentals does not support current market pricing. Despite NextEra’s scale, high-quality asset base, and long-term renewable growth profile, elevated capital intensity and balance-sheet leverage materially constrain free cash flow available to equity holders. As a result, the initial BUY thesis was disproven through valuation, leading to a SELL recommendation.
B27: Key Takeaways
B28: DCF implies material downside to current market price Capital intensity and leverage constrain equity value Trading multiples embed optimistic assumptions Rate normalization insufficient to justify valuation
B38: Valuation Overview
B40: Method | F40: Implied Share Price
B41: Discounted Cash Flow | F41: 4.43
B42: Trading Comparables | F42: 83.85
B43: Blended Target (60% DCF / 40% Comps) | F43: 36.2
B45: Conclusion
B46: While NextEra Energy remains a best-in-class operator within the utilities and renewables space, current valuation embeds assumptions that are not supported by cash flow fundamentals. Until valuation levels better reflect intrinsic value and balance-sheet dynamics improve, downside risk outweighs upside potential.
B53: Rating: SELL
B55: Prepared By
B56: Utkarsh Vikas Pandey
B57: Equity Research - Utilities & Energy
B58: 21/01/2026
B61: Disclaimer: This report has been prepared solely for academic and educational research purposes. It does not constitute financial, investment, legal, or tax advice, nor is it a recommendation to buy or sell any security. The analysis and valuation presented are based on publicly available information and assumptions that may not reflect actual outcomes. Readers should not rely on this report for investment decisions and are encouraged to conduct their own independent research and due diligence or consult a qualified financial professional before making any investment decisions. The author assumes no responsibility or liability for the use of this material.

Sheet Assumptions
B2: Years | C2: 2021 | D2: 2022 | E2: 2023 | F2: 2024 | G2: 2025 | H2: 2026 | I2: 2027 | J2: 2028 | K2: 2029 | L2: 2030
B3: Period | C3: Historical | D3: Historical | E3: Historical | F3: Historical | G3: Historical | H3: Forecast | I3: Forecast | J3: Forecast | K3: Forecast | L3: Forecast
B6: Macro Assumptions
B7: Risk free rate (10Y) | C7: 0.042
B8: ERP | C8: 0.0525
B9: Corporate Tax Rate | C9: 0.21
B11: Beta (levered) | C11: 0.7
B12: Cost of equity (Re) | C12: =C7 + C11*C8 -> 0.07875
Y13: S
B14: Cost of debt (pre-tax) | C14: 0.05
B15: Cost of debt (after-tax) | C15: =C14*(1-C9) -> 0.0395
B17: Capital Structure
B18: Equity weight (E/V) | C18: 0.6
B19: Debt weight (D/V) | C19: 0.4
B21: WACC (current) | C21: =C18*C12 + C19*C15 -> 0.06305
B23: Normalized Assumptions
B24: Risk-free rate (normalized) | C24: 0.0325
B25: Cost of debt (normalized, pre-tax) | C25: 0.0425
B26: Cost of debt (normalized, after-tax) | C26: =C25*(1-C9) -> 0.033575
B27: Terminal growth rate | C27: 0.025
B28: Cost of equity (normalized) | C28: =C24 + C11*C8 -> 0.06925
B30: WACC (normalized) | C30: =C18*C28 + C19*C26 -> 0.05498
B32: WACC glide path | C32: =C2 -> 2021 | D32: =D2 -> 2022 | E32: =E2 -> 2023 | F32: =F2 -> 2024 | G32: =G2 -> 2025 | H32: =H2 -> 2026 | I32: =I2 -> 2027 | J32: =J2 -> 2028 | ... L32: =L2 -> 2030
B33: Weight on current WACC | C33: 1 | D33: 1 | E33: 1 | F33: 1 | G33: 1 | H33: 0.9 | I33: 0.7 | J33: 0.5 | K33: 0.3 | L33: 0.1
B34: Weight on normalized WACC | C34: =1-C33 -> 0 | D34: =1-D33 -> 0 | E34: =1-E33 -> 0 | F34: =1-F33 -> 0 | G34: =1-G33 -> 0 | H34: =1-H33 -> 0.1 | I34: =1-I33 -> 0.3 | J34: =1-J33 -> 0.5 | ... L34: =1-L33 -> 0.9
B36: Blended WACC | C36: =C33*$C$21 + C34*$C$30 -> 0.06305 | D36: =D33*$C$21 + D34*$C$30 -> 0.06305 | E36: =E33*$C$21 + E34*$C$30 -> 0.06305 | F36: =F33*$C$21 + F34*$C$30 -> 0.06305 | G36: =G33*$C$21 + G34*$C$30 -> 0.06305 | H36: =H33*$C$21 + H34*$C$30 -> 0.062243 | I36: =I33*$C$21 + I34*$C$30 -> 0.060629 | J36: =J33*$C$21 + J34*$C$30 -> 0.059015 | ... L36: =L33*$C$21 + L34*$C$30 -> 0.055787
B38: Terminal maintenance capex (% of revenue) | C38: 0.105

Sheet Historicals
B2: Year | C2: 2021 | D2: 2022 | E2: 2023 | F2: 2024
B3: Period | C3: Actual | D3: Actual | E3: Actual | F3: Actual
B5: Revenue (USD bn) | C5: 17.1 | D5: 21 | E5: 28.1 | F5: 24.8
B6: Revenue growth % | C6: - | D6: =D5/C5-1 -> 0.22807018 | E6: =E5/D5-1 -> 0.33809524 | F6: =F5/E5-1 -> -0.11743772
B8: EBIT | C8: 4.45 | D8: 4.42 | E8: 10.61 | F8: 8.27
B9: EBIT Margin % | C9: =C8/C5 -> 0.26023392 | D9: =D8/D5 -> 0.21047619 | E9: =E8/E5 -> 0.37758007 | F9: =F8/F5 -> 0.33346774
B11: Depreciation & amortization | C11: 4.21 | D11: 4.79 | E11: 6.15 | F11: 5.76
B12: D&A % of revenue | C12: =C11/C5 -> 0.24619883 | D12: =D11/D5 -> 0.22809524 | E12: =E11/E5 -> 0.21886121 | F12: =F11/F5 -> 0.23225806
B14: Capital expenditures | C14: 7.83 | D14: 9.74 | E14: 9.55 | F14: 8.51
B15: Capex % of revenue | C15: =C14/C5 -> 0.45789474 | D15: =D14/D5 -> 0.46380952 | E15: =E14/E5 -> 0.33985765 | F15: =F14/F5 -> 0.34314516
B17: Change in net working capital | C17: - | D17: -5.06 | E17: 0.6 | F17: -0.8
B18: Change in NWC % of Revenue | C18: - | D18: =D17/D5 -> -0.24095238 | E18: =E17/E5 -> 0.021352313 | F18: =F17/F5 -> -0.032258065

Sheet Forecast
B2: FCFF
C3: 2021 | D3: 2022 | E3: 2023 | F3: 2024 | G3: 2025 | H3: 2026 | I3: 2027 | J3: 2028 | K3: 2029 | L3: 2030
B4: EBIT | C4: =FinStatements!C9 -> 4.104 | D4: =FinStatements!D9 -> 5.225 | E4: =FinStatements!E9 -> 5.6355 | F4: =FinStatements!F9 -> 6.5 | G4: =FinStatements!G9 -> 6.9695 | H4: =FinStatements!H9 -> 7.38767 | I4: =FinStatements!I9 -> 7.7939919 | J4: =FinStatements!J9 -> 8.1836914 | ... L4: =FinStatements!L9 -> 8.8940359
B5: Less: Cash taxes | C5: =C4 * Assumptions!$C$9 -> 0.86184 | D5: =D4 * Assumptions!$C$9 -> 1.09725 | E5: =E4 * Assumptions!$C$9 -> 1.183455 | F5: =F4 * Assumptions!$C$9 -> 1.365 | G5: =G4 * Assumptions!$C$9 -> 1.463595 | H5: =H4 * Assumptions!$C$9 -> 1.5514107 | I5: =I4 * Assumptions!$C$9 -> 1.6367383 | J5: =J4 * Assumptions!$C$9 -> 1.7185752 | ... L5: =L4 * Assumptions!$C$9 -> 1.8677475
B6: NOPAT | C6: =C4 - C5 -> 3.24216 | D6: =D4 - D5 -> 4.12775 | E6: =E4 - E5 -> 4.452045 | F6: =F4 - F5 -> 5.135 | G6: =G4 - G5 -> 5.505905 | H6: =H4 - H5 -> 5.8362593 | I6: =I4 - I5 -> 6.1572536 | J6: =J4 - J5 -> 6.4651162 | ... L6: =L4 - L5 -> 7.0262883
B7: Add: Depreciation & amortization | C7: =FinStatements!C13 -> 1.71 | D7: =FinStatements!D13 -> 2.09 | E7: =FinStatements!E13 -> 2.21 | F7: =FinStatements!F13 -> 2.5 | G7: =FinStatements!G13 -> 2.63 | H7: =FinStatements!H13 -> 2.7878 | I7: =FinStatements!I13 -> 2.941129 | J7: =FinStatements!J13 -> 3.0881855 | ... L7: =FinStatements!L13 -> 3.3562399
B8: Less: Capital expenditures | C8: =FinStatements!C15 -> 3.078 | D8: =FinStatements!D15 -> 3.971 | E8: =FinStatements!E15 -> 4.42 | F8: =FinStatements!F15 -> 5.25 | G8: =FinStatements!G15 -> 5.786 | H8: =FinStatements!H15 -> 6.13316 | I8: =FinStatements!I15 -> 6.4704838 | J8: =FinStatements!J15 -> 6.794008 | ... L8: =FinStatements!L15 -> 7.3837279
B9: Less: Change in net working capital | C9: =FinStatements!C17 -> 0.0855 | D9: =FinStatements!D17 -> 0.1045 | E9: =FinStatements!E17 -> 0.1105 | F9: =FinStatements!F17 -> 0.125 | G9: =FinStatements!G17 -> 0.1315 | H9: =FinStatements!H17 -> 0.13939 | I9: =FinStatements!I17 -> 0.14705645 | J9: =FinStatements!J17 -> 0.15440927 | ... L9: =FinStatements!L17 -> 0.167812
B10: FCFF | C10: =C6 + C7 - C8 - C9 -> 1.78866 | D10: =D6 + D7 - D8 - D9 -> 2.14225 | E10: =E6 + E7 - E8 - E9 -> 2.131545 | F10: =F6 + F7 - F8 - F9 -> 2.26 | G10: =G6 + G7 - G8 - G9 -> 2.218405 | H10: =H6 + H7 - H8 - H9 -> 2.3515093 | I10: =I6 + I7 - I8 - I9 -> 2.4808423 | J10: =J6 + J7 - J8 - J9 -> 2.6048844 | ... L10: =L6 + L7 - L8 - L9 -> 2.8309884

Sheet FinStatements
B2: Financial Statements (Operating Build)
B4: Year | C4: =Assumptions!C2 -> 2021 | D4: =Assumptions!D2 -> 2022 | E4: =Assumptions!E2 -> 2023 | F4: =Assumptions!F2 -> 2024 | G4: =Assumptions!G2 -> 2025 | H4: =Assumptions!H2 -> 2026 | I4: =Assumptions!I2 -> 2027 | J4: =Assumptions!J2 -> 2028 | ... L4: =Assumptions!L2 -> 2030
B5: USD (billions)
B6: Revenue | C6: 17.1 | D6: 20.9 | E6: 22.1 | F6: 25 | G6: 26.3 | H6: =G6*(1+H8) -> 27.878 | I6: =H6*(1+I8) -> 29.41129 | J6: =I6*(1+J8) -> 30.881855 | K6: =J6*(1+K8) -> 32.271538 | L6: =K6*(1+L8) -> 33.562399
B7: Revenue growth | C7: - | D7: =D6/C6-1 -> 0.22222222 | E7: =E6/D6-1 -> 0.057416268 | F7: =F6/E6-1 -> 0.13122172 | G7: =G6/F6-1 -> 0.052
B8: Revenue growth (forecast) | H8: 0.06 | I8: 0.055 | J8: 0.05 | K8: 0.045 | L8: 0.04
B9: EBIT | C9: =C6*C10 -> 4.104 | D9: =D6*D10 -> 5.225 | E9: =E6*E10 -> 5.6355 | F9: =F6*F10 -> 6.5 | G9: =G6*G10 -> 6.9695 | H9: =H6*H10 -> 7.38767 | I9: =I6*I10 -> 7.7939919 | J9: =J6*J10 -> 8.1836914 | ... L9: =L6*L10 -> 8.8940359
B10: EBIT margin | C10: 0.24 | D10: 0.25 | E10: 0.255 | F10: 0.26 | G10: 0.265 | H10: 0.265 | I10: 0.265 | J10: 0.265 | K10: 0.265 | L10: 0.265
B12: Depreciation & amortization | C12: 0.1 | D12: 0.1 | E12: 0.1 | F12: 0.1 | G12: 0.1 | H12: 0.1 | I12: 0.1 | J12: 0.1 | K12: 0.1 | L12: 0.1
B13: Depreciation & amortization ($) | C13: =C6*C12 -> 1.71 | D13: =D6*D12 -> 2.09 | E13: =E6*E12 -> 2.21 | F13: =F6*F12 -> 2.5 | G13: =G6*G12 -> 2.63 | H13: =H6*H12 -> 2.7878 | I13: =I6*I12 -> 2.941129 | J13: =J6*J12 -> 3.0881855 | ... L13: =L6*L12 -> 3.3562399
B14: Capital expenditures | C14: 0.18 | D14: 0.19 | E14: 0.2 | F14: 0.21 | G14: 0.22 | H14: 0.22 | I14: 0.22 | J14: 0.22 | K14: 0.22 | L14: 0.22
B15: Capital expenditures ($) | C15: =C6*C14 -> 3.078 | D15: =D6*D14 -> 3.971 | E15: =E6*E14 -> 4.42 | F15: =F6*F14 -> 5.25 | G15: =G6*G14 -> 5.786 | H15: =H6*H14 -> 6.13316 | I15: =I6*I14 -> 6.4704838 | J15: =J6*J14 -> 6.794008 | ... L15: =L6*L14 -> 7.3837279
B16: Change in net working capital | C16: 0.005 | D16: 0.005 | E16: 0.005 | F16: 0.005 | G16: 0.005 | H16: 0.005 | I16: 0.005 | J16: 0.005 | K16: 0.005 | L16: 0.005
B17: Change in net working capital ($) | C17: =C6*C16 -> 0.0855 | D17: =D6*D16 -> 0.1045 | E17: =E6*E16 -> 0.1105 | F17: =F6*F16 -> 0.125 | G17: =G6*G16 -> 0.1315 | H17: =H6*H16 -> 0.13939 | I17: =I6*I16 -> 0.14705645 | J17: =J6*J16 -> 0.15440927 | ... L17: =L6*L16 -> 0.167812
B18: FCFF | C18: =C9*(1-$C$10)+C13-C15-C17 -> 1.66554 | D18: =D9*(1-$C$10)+D13-D15-D17 -> 1.9855 | E18: =E9*(1-$C$10)+E13-E15-E17 -> 1.96248 | F18: =F9*(1-$C$10)+F13-F15-F17 -> 2.065 | G18: =G9*(1-$C$10)+G13-G15-G17 -> 2.00932 | H18: =H9*(1-$C$10)+H13-H15-H17 -> 2.1298792 | I18: =I9*(1-$C$10)+I13-I15-I17 -> 2.2470226 | J18: =J9*(1-$C$10)+J13-J15-J17 -> 2.3593737 | ... L18: =L9*(1-$C$10)+L13-L15-L17 -> 2.5641673

Sheet WACC
B2: WACC Inputs
B3: Risk-free rate | C3: =Assumptions!C7 -> 0.042
B4: Equity Risk Premium | C4: =Assumptions!C8 -> 0.0525
B5: Levered Beta | C5: =Assumptions!C11 -> 0.7
B6: Cost of Equity | C6: =Assumptions!C12 -> 0.07875
B8: Pre-tax Cost of Debt | C8: =Assumptions!C14 -> 0.05
B9: Tax Rate | C9: =Assumptions!C9 -> 0.21
B10: After-tax Cost of Debt | C10: =C8 * (1 - C9) -> 0.0395
B12: Capital Structure
B13: Equity Weight | C13: =Assumptions!C18 -> 0.6
B14: Debt Weight | C14: =Assumptions!C19 -> 0.4
B16: WACC (Current) | C16: =C13*C6 + C14*C10 -> 0.06305
B17: WACC (Normalized) | C17: =Assumptions!C30 -> 0.05498

Sheet DCF
B2: DCF
B3: All Figures in USD Billions
B5: Year | C5: =Assumptions!C2 -> 2021 | D5: =Assumptions!D2 -> 2022 | E5: =Assumptions!E2 -> 2023 | F5: =Assumptions!F2 -> 2024 | G5: =Assumptions!G2 -> 2025 | H5: =Assumptions!H2 -> 2026 | I5: =Assumptions!I2 -> 2027 | J5: =Assumptions!J2 -> 2028 | ... L5: =Assumptions!L2 -> 2030
B6: Year # | C6: 0 | D6: =C6+1 -> 1 | E6: =D6+1 -> 2 | F6: =E6+1 -> 3 | G6: =F6+1 -> 4 | H6: =G6+1 -> 5 | I6: =H6+1 -> 6 | J6: =I6+1 -> 7 | K6: =J6+1 -> 8 | L6: =K6+1 -> 9
B8: Blended WACC | C8: =Assumptions!C36 -> 0.06305 | D8: =Assumptions!D36 -> 0.06305 | E8: =Assumptions!E36 -> 0.06305 | F8: =Assumptions!F36 -> 0.06305 | G8: =Assumptions!G36 -> 0.06305 | H8: =Assumptions!H36 -> 0.062243 | I8: =Assumptions!I36 -> 0.060629 | J8: =Assumptions!J36 -> 0.059015 | ... L8: =Assumptions!L36 -> 0.055787
B9: Discount factor | C9: =1/(1+C8)^C6 -> 1 | D9: =1/(1+D8)^D6 -> 0.94068953 | E9: =1/(1+E8)^E6 -> 0.88489678 | F9: =1/(1+F8)^F6 -> 0.83241314 | G9: =1/(1+G8)^G6 -> 0.78304232 | H9: =1/(1+H8)^H6 -> 0.73940198 | I9: =1/(1+I8)^I6 -> 0.70245582 | J9: =1/(1+J8)^J6 -> 0.66939925 | ... L9: =1/(1+L8)^L6 -> 0.61349808
B11: FCFF | C11: =FinStatements!C18 -> 1.66554 | D11: =FinStatements!D18 -> 1.9855 | E11: =FinStatements!E18 -> 1.96248 | F11: =FinStatements!F18 -> 2.065 | G11: =FinStatements!G18 -> 2.00932 | H11: =FinStatements!H18 -> 2.1298792 | I11: =FinStatements!I18 -> 2.2470226 | J11: =FinStatements!J18 -> 2.3593737 | ... L11: =FinStatements!L18 -> 2.5641673
B12: PV of FCFF | C12: =C11*C9 -> 1.66554 | D12: =D11*D9 -> 1.8677391 | E12: =E11*E9 -> 1.7365922 | F12: =F11*F9 -> 1.7189331 | G12: =G11*G9 -> 1.5733826 | H12: =H11*H9 -> 1.5748369 | I12: =I11*I9 -> 1.5784341 | J12: =J11*J9 -> 1.579363 | ... L12: =L11*L9 -> 1.5731117
B14: Terminal FCFF (normalized) | L14: =FinStatements!L9*(1-Assumptions!C9) + FinStatements!L12 - FinStatements!L6*Assumptions!C38 - FinStatements!L16 -> 3.5972364
B15: Terminal Value | L15: =L14*(1+Assumptions!C27)/(L8-Assumptions!C27) -> 119.76377
B16: PV of Terminal Value | L16: =L15*L9 -> 73.474845
B18: Enterprise Value | L18: =SUM(C12:L12)+L16 -> 89.920372
B19: Less: Net Debt | L19: 80.8
B20: Equity Value | L20: =L18-L19 -> 9.120372

Sheet Comps
B2: Comps (Trading Multiples)
B4: Input
B5: Share Price | C5: 83.85
B6: Shares Outstanding (mm) | C6: 2057
B7: Net Debt | C7: 80.8
B8: Tax Rate | C8: 0.21
B10: Market Value
B11: Market Cap | C11: =C5 * C6 -> 172479.45
B12: Enterprise Value | C12: =C11 + C7 -> 172560.25
B14: Operating (TTM)
B15: Revenue | C15: 26300
B16: EBITDA | C16: 14330
B17: EBITD | C17: 7520
B18: Net Income | C18: 6500
B20: Multiples
B21: EV / Revenue | C21: =C12 / C15 -> 6.5612262
B22: EV / EBITDA | C22: =C12/C16 -> 12.041888
B23: EV / EBIT | C23: =C12/C17 -> 22.946842
B24: P / E | C24: =C11/C18 -> 26.5353

Sheet Output
B2: Valuation Summary
B4: DCF Valuation
B5: Enterprise Value | F5: =DCF!L18 -> 89.920372
B6: Less: Net Debt | F6: =DCF!L19 -> 80.8
B7: Equity Value | F7: =DCF!L20 -> 9.120372
B8: Shares Outstanding | F8: =Comps!C6 -> 2057
B9: Implied Share Price | F9: =(F7*1000)/F8 -> 4.4338221
B11: Trading Comps Valuation
B12: Current Share Price | F12: =Comps!C5 -> 83.85
B13: Implied Multiple (EV/EBITDA) | F13: =Comps!C22 -> 12.041888
B14: Implied Share Price (Comps) | F14: =((Comps!C22 * Comps!C16) - Comps!C7) / Comps!C6 -> 83.85
B16: Valuation Conclusion
B17: DCF Weight | F17: 0.6
B18: Comps Weight | F18: 0.4
B19: Blended Price Target | F19: =(F9*0.6)+(F14*0.4) -> 36.200293
B20: Upside / (Downside) | F20: =(F19/F12)-1 -> -0.56827319
B21: Rating | F21: SELL
